{
  "version": "2",
  "users": [
    {
      "name": "User",
      "password": {
        "hash": "Kf0wXj3VraEUfrJL2hDtfsNLyIpHWY2nmqBXLn0xMkK++iZFWOAyhW+GPjVjy6nIsSKjZJLrHC6SUpLHiD51Zw==",
        "salt": "tSlm3Dr1MLP8XahUngIn8s70k2ZNpMhfDk4arioFSRk=",
        "algorithm": "PBKDF2-HMAC-SHA1",
        "encoding": "utf16le",
        "iteration": 10000
      },
      "fullname": "User",
      "comment": "",
      "alertbeforepasswordexpirationdays": 0,
      "passwordexpirationdays": 0,
      "autologoff": 30
    },
    {
      "name": "AdminHMI",
      "password": {
        "hash": "H/d1yRofFCZv0zMy760gmiNfSjuxe+Rodb8KTHbX/p8NdlTntHiG49JKYQlhju+0hh27a1TIUK0IYUrYVsOzfQ==",
        "salt": "uF0lpw6RRasdGcDiTiRA/djvl99WvF9pcLzHUDqQvoo=",
        "algorithm": "PBKDF2-HMAC-SHA1",
        "encoding": "utf16le",
        "iteration": 10000
      },
      "fullname": "AdminHMI",
      "comment": "",
      "alertbeforepasswordexpirationdays": 0,
      "passwordexpirationdays": 0,
      "autologoff": 30
    }
  ],
  "groups": [
    {
      "name": "HMI Administrator",
      "roles": [
        "HMI Administrator"
      ],
      "users": [
        "AdminHMI"
      ]
    },
    {
      "name": "HMI Operator",
      "users": [
        "User",
        "AdminHMI"
      ]
    },
    {
      "name": "HMI Monitor",
      "users": [
        "User",
        "AdminHMI"
      ]
    },
    {
      "name": "HMI Monitor Client",
      "users": [
        "User",
        "AdminHMI"
      ]
    }
  ],
  "roles": [
    {
      "name": "HMI Administrator",
      "rights": [
        "UM_ADMIN",
        "UM_IMPORT",
        "UM_EXPORT",
        "UM_VIEW",
        "UM_RESETPWD"
      ]
    }
  ],
  "globalAccountPolicies": {
    "enableLockAfterNumberOfAttempts": 0,
    "enablePasswordHistoryByDays": 0,
    "enablePasswordHistoryByNumber": 1,
    "enablePasswordCheck": 1,
    "maxLoginErrors": 0,
    "numberOfPasswordBeforeReuse": 5,
    "passwordAging": 0,
    "passwordMaxLength": 120,
    "passwordMinAlphaChar": 0,
    "passwordMinLength": 10,
    "passwordMinLowerChar": 1,
    "passwordMinUpperChar": 1,
    "passwordMinNumericChar": 1,
    "passwordMinOtherChar": 0
  },
  "umcConfig": {
    "local": {
      "domainName": "UM_Domain"
    }
  }
}